{
  "scatter_points": [
    {
      "actual": 2.54,
      "predicted": 2.6,
      "district": "Bagerhat",
      "season": "Aman"
    },
    {
      "actual": 2.72,
      "predicted": 2.58,
      "district": "Bagerhat",
      "season": "Aman"
    },
    {
      "actual": 2.12,
      "predicted": 2.17,
      "district": "Bagerhat",
      "season": "Aus"
    },
    {
      "actual": 2.17,
      "predicted": 2.07,
      "district": "Bagerhat",
      "season": "Aus"
    },
    {
      "actual": 4.29,
      "predicted": 4.25,
      "district": "Bagerhat",
      "season": "Boro"
    },
    {
      "actual": 4.46,
      "predicted": 3.95,
      "district": "Bagerhat",
      "season": "Boro"
    },
    {
      "actual": 1.97,
      "predicted": 2.02,
      "district": "Bandarban",
      "season": "Aman"
    },
    {
      "actual": 1.99,
      "predicted": 1.91,
      "district": "Bandarban",
      "season": "Aman"
    },
    {
      "actual": 1.58,
      "predicted": 1.57,
      "district": "Bandarban",
      "season": "Aus"
    },
    {
      "actual": 1.6,
      "predicted": 1.6,
      "district": "Bandarban",
      "season": "Aus"
    },
    {
      "actual": 3.06,
      "predicted": 3.16,
      "district": "Bandarban",
      "season": "Boro"
    },
    {
      "actual": 3.28,
      "predicted": 3.12,
      "district": "Bandarban",
      "season": "Boro"
    },
    {
      "actual": 2.6,
      "predicted": 2.56,
      "district": "Barguna",
      "season": "Aman"
    },
    {
      "actual": 2.66,
      "predicted": 2.59,
      "district": "Barguna",
      "season": "Aman"
    },
    {
      "actual": 2.06,
      "predicted": 2.12,
      "district": "Barguna",
      "season": "Aus"
    },
    {
      "actual": 2.22,
      "predicted": 2.06,
      "district": "Barguna",
      "season": "Aus"
    },
    {
      "actual": 4.07,
      "predicted": 4.27,
      "district": "Barguna",
      "season": "Boro"
    },
    {
      "actual": 4.35,
      "predicted": 3.87,
      "district": "Barguna",
      "season": "Boro"
    },
    {
      "actual": 2.57,
      "predicted": 2.56,
      "district": "Barishal",
      "season": "Aman"
    },
    {
      "actual": 2.66,
      "predicted": 2.59,
      "district": "Barishal",
      "season": "Aman"
    },
    {
      "actual": 2.06,
      "predicted": 2.12,
      "district": "Barishal",
      "season": "Aus"
    },
    {
      "actual": 2.17,
      "predicted": 2.07,
      "district": "Barishal",
      "season": "Aus"
    },
    {
      "actual": 4.23,
      "predicted": 4.29,
      "district": "Barishal",
      "season": "Boro"
    },
    {
      "actual": 4.42,
      "predicted": 3.9,
      "district": "Barishal",
      "season": "Boro"
    },
    {
      "actual": 2.5,
      "predicted": 2.51,
      "district": "Bhola",
      "season": "Aman"
    },
    {
      "actual": 2.61,
      "predicted": 2.59,
      "district": "Bhola",
      "season": "Aman"
    },
    {
      "actual": 2.09,
      "predicted": 2.13,
      "district": "Bhola",
      "season": "Aus"
    },
    {
      "actual": 2.16,
      "predicted": 2.06,
      "district": "Bhola",
      "season": "Aus"
    },
    {
      "actual": 4.34,
      "predicted": 4.28,
      "district": "Bhola",
      "season": "Boro"
    },
    {
      "actual": 4.39,
      "predicted": 3.94,
      "district": "Bhola",
      "season": "Boro"
    },
    {
      "actual": 2.9,
      "predicted": 2.92,
      "district": "Bogura",
      "season": "Aman"
    },
    {
      "actual": 3.12,
      "predicted": 2.91,
      "district": "Bogura",
      "season": "Aman"
    },
    {
      "actual": 2.38,
      "predicted": 2.38,
      "district": "Bogura",
      "season": "Aus"
    },
    {
      "actual": 2.41,
      "predicted": 2.36,
      "district": "Bogura",
      "season": "Aus"
    },
    {
      "actual": 4.85,
      "predicted": 4.74,
      "district": "Bogura",
      "season": "Boro"
    },
    {
      "actual": 5.07,
      "predicted": 4.69,
      "district": "Bogura",
      "season": "Boro"
    },
    {
      "actual": 2.6,
      "predicted": 2.55,
      "district": "Brahmanbaria",
      "season": "Aman"
    },
    {
      "actual": 2.73,
      "predicted": 2.59,
      "district": "Brahmanbaria",
      "season": "Aman"
    },
    {
      "actual": 2.1,
      "predicted": 2.13,
      "district": "Brahmanbaria",
      "season": "Aus"
    },
    {
      "actual": 2.09,
      "predicted": 2.09,
      "district": "Brahmanbaria",
      "season": "Aus"
    },
    {
      "actual": 4.28,
      "predicted": 4.24,
      "district": "Brahmanbaria",
      "season": "Boro"
    },
    {
      "actual": 4.29,
      "predicted": 3.93,
      "district": "Brahmanbaria",
      "season": "Boro"
    },
    {
      "actual": 2.6,
      "predicted": 2.58,
      "district": "Chandpur",
      "season": "Aman"
    },
    {
      "actual": 2.76,
      "predicted": 2.6,
      "district": "Chandpur",
      "season": "Aman"
    },
    {
      "actual": 2.07,
      "predicted": 2.13,
      "district": "Chandpur",
      "season": "Aus"
    },
    {
      "actual": 2.19,
      "predicted": 2.07,
      "district": "Chandpur",
      "season": "Aus"
    },
    {
      "actual": 4.14,
      "predicted": 4.08,
      "district": "Chandpur",
      "season": "Boro"
    },
    {
      "actual": 4.29,
      "predicted": 3.93,
      "district": "Chandpur",
      "season": "Boro"
    },
    {
      "actual": 2.52,
      "predicted": 2.57,
      "district": "Chapainawabganj",
      "season": "Aman"
    },
    {
      "actual": 2.66,
      "predicted": 2.59,
      "district": "Chapainawabganj",
      "season": "Aman"
    },
    {
      "actual": 2.09,
      "predicted": 2.16,
      "district": "Chapainawabganj",
      "season": "Aus"
    },
    {
      "actual": 2.16,
      "predicted": 2.09,
      "district": "Chapainawabganj",
      "season": "Aus"
    },
    {
      "actual": 4.22,
      "predicted": 4.28,
      "district": "Chapainawabganj",
      "season": "Boro"
    },
    {
      "actual": 4.28,
      "predicted": 3.89,
      "district": "Chapainawabganj",
      "season": "Boro"
    },
    {
      "actual": 2.64,
      "predicted": 2.56,
      "district": "Chattogram",
      "season": "Aman"
    },
    {
      "actual": 2.6,
      "predicted": 2.62,
      "district": "Chattogram",
      "season": "Aman"
    },
    {
      "actual": 2.15,
      "predicted": 2.14,
      "district": "Chattogram",
      "season": "Aus"
    },
    {
      "actual": 2.23,
      "predicted": 2.09,
      "district": "Chattogram",
      "season": "Aus"
    },
    {
      "actual": 4.3,
      "predicted": 4.23,
      "district": "Chattogram",
      "season": "Boro"
    },
    {
      "actual": 4.25,
      "predicted": 3.94,
      "district": "Chattogram",
      "season": "Boro"
    },
    {
      "actual": 2.64,
      "predicted": 2.54,
      "district": "Chuadanga",
      "season": "Aman"
    },
    {
      "actual": 2.77,
      "predicted": 2.64,
      "district": "Chuadanga",
      "season": "Aman"
    },
    {
      "actual": 2.09,
      "predicted": 2.14,
      "district": "Chuadanga",
      "season": "Aus"
    },
    {
      "actual": 2.22,
      "predicted": 2.08,
      "district": "Chuadanga",
      "season": "Aus"
    },
    {
      "actual": 4.32,
      "predicted": 4.28,
      "district": "Chuadanga",
      "season": "Boro"
    },
    {
      "actual": 4.35,
      "predicted": 3.94,
      "district": "Chuadanga",
      "season": "Boro"
    },
    {
      "actual": 2.58,
      "predicted": 2.53,
      "district": "Cox'S Bazar",
      "season": "Aman"
    },
    {
      "actual": 2.79,
      "predicted": 2.62,
      "district": "Cox'S Bazar",
      "season": "Aman"
    },
    {
      "actual": 2.1,
      "predicted": 2.12,
      "district": "Cox'S Bazar",
      "season": "Aus"
    },
    {
      "actual": 2.13,
      "predicted": 2.08,
      "district": "Cox'S Bazar",
      "season": "Aus"
    },
    {
      "actual": 4.22,
      "predicted": 4.25,
      "district": "Cox'S Bazar",
      "season": "Boro"
    },
    {
      "actual": 4.34,
      "predicted": 3.93,
      "district": "Cox'S Bazar",
      "season": "Boro"
    },
    {
      "actual": 2.95,
      "predicted": 2.76,
      "district": "Cumilla",
      "season": "Aman"
    },
    {
      "actual": 2.99,
      "predicted": 2.84,
      "district": "Cumilla",
      "season": "Aman"
    },
    {
      "actual": 2.2,
      "predicted": 2.27,
      "district": "Cumilla",
      "season": "Aus"
    },
    {
      "actual": 2.3,
      "predicted": 2.25,
      "district": "Cumilla",
      "season": "Aus"
    },
    {
      "actual": 4.66,
      "predicted": 4.56,
      "district": "Cumilla",
      "season": "Boro"
    },
    {
      "actual": 4.63,
      "predicted": 4.47,
      "district": "Cumilla",
      "season": "Boro"
    },
    {
      "actual": 2.44,
      "predicted": 2.39,
      "district": "Dhaka",
      "season": "Aman"
    },
    {
      "actual": 2.52,
      "predicted": 2.37,
      "district": "Dhaka",
      "season": "Aman"
    },
    {
      "actual": 1.97,
      "predicted": 2.11,
      "district": "Dhaka",
      "season": "Aus"
    },
    {
      "actual": 1.97,
      "predicted": 2.03,
      "district": "Dhaka",
      "season": "Aus"
    },
    {
      "actual": 4.06,
      "predicted": 4.08,
      "district": "Dhaka",
      "season": "Boro"
    },
    {
      "actual": 4.14,
      "predicted": 3.81,
      "district": "Dhaka",
      "season": "Boro"
    },
    {
      "actual": 3.08,
      "predicted": 3.02,
      "district": "Dinajpur",
      "season": "Aman"
    },
    {
      "actual": 3.23,
      "predicted": 3.03,
      "district": "Dinajpur",
      "season": "Aman"
    },
    {
      "actual": 2.45,
      "predicted": 2.49,
      "district": "Dinajpur",
      "season": "Aus"
    },
    {
      "actual": 2.49,
      "predicted": 2.41,
      "district": "Dinajpur",
      "season": "Aus"
    },
    {
      "actual": 4.97,
      "predicted": 4.92,
      "district": "Dinajpur",
      "season": "Boro"
    },
    {
      "actual": 5.11,
      "predicted": 4.75,
      "district": "Dinajpur",
      "season": "Boro"
    },
    {
      "actual": 2.56,
      "predicted": 2.55,
      "district": "Faridpur",
      "season": "Aman"
    },
    {
      "actual": 2.64,
      "predicted": 2.59,
      "district": "Faridpur",
      "season": "Aman"
    },
    {
      "actual": 2.09,
      "predicted": 2.15,
      "district": "Faridpur",
      "season": "Aus"
    },
    {
      "actual": 2.19,
      "predicted": 2.09,
      "district": "Faridpur",
      "season": "Aus"
    },
    {
      "actual": 4.22,
      "predicted": 4.25,
      "district": "Faridpur",
      "season": "Boro"
    },
    {
      "actual": 4.32,
      "predicted": 3.93,
      "district": "Faridpur",
      "season": "Boro"
    },
    {
      "actual": 2.63,
      "predicted": 2.55,
      "district": "Feni",
      "season": "Aman"
    },
    {
      "actual": 2.72,
      "predicted": 2.57,
      "district": "Feni",
      "season": "Aman"
    },
    {
      "actual": 2.04,
      "predicted": 2.12,
      "district": "Feni",
      "season": "Aus"
    },
    {
      "actual": 2.26,
      "predicted": 2.06,
      "district": "Feni",
      "season": "Aus"
    },
    {
      "actual": 4.0,
      "predicted": 4.27,
      "district": "Feni",
      "season": "Boro"
    },
    {
      "actual": 4.3,
      "predicted": 3.8,
      "district": "Feni",
      "season": "Boro"
    },
    {
      "actual": 2.66,
      "predicted": 2.55,
      "district": "Gaibandha",
      "season": "Aman"
    },
    {
      "actual": 2.67,
      "predicted": 2.65,
      "district": "Gaibandha",
      "season": "Aman"
    },
    {
      "actual": 2.04,
      "predicted": 2.11,
      "district": "Gaibandha",
      "season": "Aus"
    },
    {
      "actual": 2.17,
      "predicted": 2.08,
      "district": "Gaibandha",
      "season": "Aus"
    },
    {
      "actual": 4.18,
      "predicted": 4.26,
      "district": "Gaibandha",
      "season": "Boro"
    },
    {
      "actual": 4.28,
      "predicted": 3.9,
      "district": "Gaibandha",
      "season": "Boro"
    },
    {
      "actual": 2.59,
      "predicted": 2.54,
      "district": "Gazipur",
      "season": "Aman"
    },
    {
      "actual": 2.7,
      "predicted": 2.62,
      "district": "Gazipur",
      "season": "Aman"
    },
    {
      "actual": 2.1,
      "predicted": 2.14,
      "district": "Gazipur",
      "season": "Aus"
    },
    {
      "actual": 2.12,
      "predicted": 2.1,
      "district": "Gazipur",
      "season": "Aus"
    },
    {
      "actual": 4.15,
      "predicted": 4.2,
      "district": "Gazipur",
      "season": "Boro"
    },
    {
      "actual": 4.32,
      "predicted": 3.9,
      "district": "Gazipur",
      "season": "Boro"
    },
    {
      "actual": 2.65,
      "predicted": 2.54,
      "district": "Gopalganj",
      "season": "Aman"
    },
    {
      "actual": 2.58,
      "predicted": 2.65,
      "district": "Gopalganj",
      "season": "Aman"
    },
    {
      "actual": 2.16,
      "predicted": 2.12,
      "district": "Gopalganj",
      "season": "Aus"
    },
    {
      "actual": 2.18,
      "predicted": 2.11,
      "district": "Gopalganj",
      "season": "Aus"
    },
    {
      "actual": 4.3,
      "predicted": 4.23,
      "district": "Gopalganj",
      "season": "Boro"
    },
    {
      "actual": 4.13,
      "predicted": 3.93,
      "district": "Gopalganj",
      "season": "Boro"
    },
    {
      "actual": 2.13,
      "predicted": 2.6,
      "district": "Habiganj",
      "season": "Aman"
    },
    {
      "actual": 2.66,
      "predicted": 2.42,
      "district": "Habiganj",
      "season": "Aman"
    },
    {
      "actual": 1.69,
      "predicted": 2.12,
      "district": "Habiganj",
      "season": "Aus"
    },
    {
      "actual": 2.18,
      "predicted": 1.94,
      "district": "Habiganj",
      "season": "Aus"
    },
    {
      "actual": 3.39,
      "predicted": 4.18,
      "district": "Habiganj",
      "season": "Boro"
    },
    {
      "actual": 4.23,
      "predicted": 3.71,
      "district": "Habiganj",
      "season": "Boro"
    },
    {
      "actual": 2.57,
      "predicted": 2.58,
      "district": "Jamalpur",
      "season": "Aman"
    },
    {
      "actual": 2.65,
      "predicted": 2.61,
      "district": "Jamalpur",
      "season": "Aman"
    },
    {
      "actual": 2.09,
      "predicted": 2.11,
      "district": "Jamalpur",
      "season": "Aus"
    },
    {
      "actual": 2.14,
      "predicted": 2.08,
      "district": "Jamalpur",
      "season": "Aus"
    },
    {
      "actual": 4.14,
      "predicted": 4.25,
      "district": "Jamalpur",
      "season": "Boro"
    },
    {
      "actual": 4.23,
      "predicted": 3.88,
      "district": "Jamalpur",
      "season": "Boro"
    },
    {
      "actual": 2.91,
      "predicted": 2.82,
      "district": "Jashore",
      "season": "Aman"
    },
    {
      "actual": 2.91,
      "predicted": 2.85,
      "district": "Jashore",
      "season": "Aman"
    },
    {
      "actual": 2.35,
      "predicted": 2.25,
      "district": "Jashore",
      "season": "Aus"
    },
    {
      "actual": 2.36,
      "predicted": 2.32,
      "district": "Jashore",
      "season": "Aus"
    },
    {
      "actual": 4.64,
      "predicted": 4.59,
      "district": "Jashore",
      "season": "Boro"
    },
    {
      "actual": 4.66,
      "predicted": 4.39,
      "district": "Jashore",
      "season": "Boro"
    },
    {
      "actual": 2.68,
      "predicted": 2.56,
      "district": "Jhalokati",
      "season": "Aman"
    },
    {
      "actual": 2.54,
      "predicted": 2.65,
      "district": "Jhalokati",
      "season": "Aman"
    },
    {
      "actual": 2.13,
      "predicted": 2.11,
      "district": "Jhalokati",
      "season": "Aus"
    },
    {
      "actual": 2.14,
      "predicted": 2.08,
      "district": "Jhalokati",
      "season": "Aus"
    },
    {
      "actual": 4.16,
      "predicted": 4.25,
      "district": "Jhalokati",
      "season": "Boro"
    },
    {
      "actual": 4.33,
      "predicted": 3.88,
      "district": "Jhalokati",
      "season": "Boro"
    },
    {
      "actual": 2.59,
      "predicted": 2.55,
      "district": "Jhenaidah",
      "season": "Aman"
    },
    {
      "actual": 2.61,
      "predicted": 2.62,
      "district": "Jhenaidah",
      "season": "Aman"
    },
    {
      "actual": 2.12,
      "predicted": 2.15,
      "district": "Jhenaidah",
      "season": "Aus"
    },
    {
      "actual": 2.21,
      "predicted": 2.09,
      "district": "Jhenaidah",
      "season": "Aus"
    },
    {
      "actual": 4.17,
      "predicted": 4.21,
      "district": "Jhenaidah",
      "season": "Boro"
    },
    {
      "actual": 4.42,
      "predicted": 3.93,
      "district": "Jhenaidah",
      "season": "Boro"
    },
    {
      "actual": 2.69,
      "predicted": 2.57,
      "district": "Joypurhat",
      "season": "Aman"
    },
    {
      "actual": 2.66,
      "predicted": 2.64,
      "district": "Joypurhat",
      "season": "Aman"
    },
    {
      "actual": 2.02,
      "predicted": 2.14,
      "district": "Joypurhat",
      "season": "Aus"
    },
    {
      "actual": 2.13,
      "predicted": 2.06,
      "district": "Joypurhat",
      "season": "Aus"
    },
    {
      "actual": 4.2,
      "predicted": 4.25,
      "district": "Joypurhat",
      "season": "Boro"
    },
    {
      "actual": 4.35,
      "predicted": 3.9,
      "district": "Joypurhat",
      "season": "Boro"
    },
    {
      "actual": 2.03,
      "predicted": 2.08,
      "district": "Khagrachhari",
      "season": "Aman"
    },
    {
      "actual": 2.18,
      "predicted": 2.12,
      "district": "Khagrachhari",
      "season": "Aman"
    },
    {
      "actual": 1.67,
      "predicted": 1.7,
      "district": "Khagrachhari",
      "season": "Aus"
    },
    {
      "actual": 1.67,
      "predicted": 1.71,
      "district": "Khagrachhari",
      "season": "Aus"
    },
    {
      "actual": 3.44,
      "predicted": 3.32,
      "district": "Khagrachhari",
      "season": "Boro"
    },
    {
      "actual": 3.43,
      "predicted": 3.25,
      "district": "Khagrachhari",
      "season": "Boro"
    },
    {
      "actual": 2.61,
      "predicted": 2.54,
      "district": "Khulna",
      "season": "Aman"
    },
    {
      "actual": 2.69,
      "predicted": 2.62,
      "district": "Khulna",
      "season": "Aman"
    },
    {
      "actual": 2.13,
      "predicted": 2.12,
      "district": "Khulna",
      "season": "Aus"
    },
    {
      "actual": 2.14,
      "predicted": 2.1,
      "district": "Khulna",
      "season": "Aus"
    },
    {
      "actual": 4.14,
      "predicted": 4.24,
      "district": "Khulna",
      "season": "Boro"
    },
    {
      "actual": 4.35,
      "predicted": 3.86,
      "district": "Khulna",
      "season": "Boro"
    },
    {
      "actual": 2.53,
      "predicted": 2.54,
      "district": "Kishoreganj",
      "season": "Aman"
    },
    {
      "actual": 2.66,
      "predicted": 2.61,
      "district": "Kishoreganj",
      "season": "Aman"
    },
    {
      "actual": 2.09,
      "predicted": 2.16,
      "district": "Kishoreganj",
      "season": "Aus"
    },
    {
      "actual": 2.09,
      "predicted": 2.08,
      "district": "Kishoreganj",
      "season": "Aus"
    },
    {
      "actual": 4.32,
      "predicted": 4.21,
      "district": "Kishoreganj",
      "season": "Boro"
    },
    {
      "actual": 4.3,
      "predicted": 3.95,
      "district": "Kishoreganj",
      "season": "Boro"
    },
    {
      "actual": 2.64,
      "predicted": 2.53,
      "district": "Kurigram",
      "season": "Aman"
    },
    {
      "actual": 2.77,
      "predicted": 2.65,
      "district": "Kurigram",
      "season": "Aman"
    },
    {
      "actual": 2.03,
      "predicted": 2.11,
      "district": "Kurigram",
      "season": "Aus"
    },
    {
      "actual": 2.18,
      "predicted": 2.07,
      "district": "Kurigram",
      "season": "Aus"
    },
    {
      "actual": 4.3,
      "predicted": 4.32,
      "district": "Kurigram",
      "season": "Boro"
    },
    {
      "actual": 4.24,
      "predicted": 3.92,
      "district": "Kurigram",
      "season": "Boro"
    },
    {
      "actual": 2.66,
      "predicted": 2.53,
      "district": "Kushtia",
      "season": "Aman"
    },
    {
      "actual": 2.65,
      "predicted": 2.65,
      "district": "Kushtia",
      "season": "Aman"
    },
    {
      "actual": 2.03,
      "predicted": 2.12,
      "district": "Kushtia",
      "season": "Aus"
    },
    {
      "actual": 2.18,
      "predicted": 2.07,
      "district": "Kushtia",
      "season": "Aus"
    },
    {
      "actual": 3.95,
      "predicted": 4.3,
      "district": "Kushtia",
      "season": "Boro"
    },
    {
      "actual": 4.4,
      "predicted": 3.8,
      "district": "Kushtia",
      "season": "Boro"
    },
    {
      "actual": 2.6,
      "predicted": 2.53,
      "district": "Lakshmipur",
      "season": "Aman"
    },
    {
      "actual": 2.58,
      "predicted": 2.61,
      "district": "Lakshmipur",
      "season": "Aman"
    },
    {
      "actual": 2.12,
      "predicted": 2.14,
      "district": "Lakshmipur",
      "season": "Aus"
    },
    {
      "actual": 2.26,
      "predicted": 2.08,
      "district": "Lakshmipur",
      "season": "Aus"
    },
    {
      "actual": 4.32,
      "predicted": 4.23,
      "district": "Lakshmipur",
      "season": "Boro"
    },
    {
      "actual": 4.34,
      "predicted": 3.96,
      "district": "Lakshmipur",
      "season": "Boro"
    },
    {
      "actual": 2.54,
      "predicted": 2.55,
      "district": "Lalmonirhat",
      "season": "Aman"
    },
    {
      "actual": 2.66,
      "predicted": 2.6,
      "district": "Lalmonirhat",
      "season": "Aman"
    },
    {
      "actual": 2.12,
      "predicted": 2.17,
      "district": "Lalmonirhat",
      "season": "Aus"
    },
    {
      "actual": 2.11,
      "predicted": 2.15,
      "district": "Lalmonirhat",
      "season": "Aus"
    },
    {
      "actual": 4.1,
      "predicted": 4.3,
      "district": "Lalmonirhat",
      "season": "Boro"
    },
    {
      "actual": 4.38,
      "predicted": 3.87,
      "district": "Lalmonirhat",
      "season": "Boro"
    },
    {
      "actual": 2.62,
      "predicted": 2.52,
      "district": "Madaripur",
      "season": "Aman"
    },
    {
      "actual": 2.69,
      "predicted": 2.64,
      "district": "Madaripur",
      "season": "Aman"
    },
    {
      "actual": 2.08,
      "predicted": 2.13,
      "district": "Madaripur",
      "season": "Aus"
    },
    {
      "actual": 2.11,
      "predicted": 2.08,
      "district": "Madaripur",
      "season": "Aus"
    },
    {
      "actual": 4.28,
      "predicted": 4.25,
      "district": "Madaripur",
      "season": "Boro"
    },
    {
      "actual": 4.18,
      "predicted": 3.93,
      "district": "Madaripur",
      "season": "Boro"
    },
    {
      "actual": 2.59,
      "predicted": 2.55,
      "district": "Magura",
      "season": "Aman"
    },
    {
      "actual": 2.76,
      "predicted": 2.62,
      "district": "Magura",
      "season": "Aman"
    },
    {
      "actual": 2.11,
      "predicted": 2.12,
      "district": "Magura",
      "season": "Aus"
    },
    {
      "actual": 2.14,
      "predicted": 2.1,
      "district": "Magura",
      "season": "Aus"
    },
    {
      "actual": 4.09,
      "predicted": 4.27,
      "district": "Magura",
      "season": "Boro"
    },
    {
      "actual": 4.29,
      "predicted": 3.87,
      "district": "Magura",
      "season": "Boro"
    },
    {
      "actual": 2.61,
      "predicted": 2.51,
      "district": "Manikganj",
      "season": "Aman"
    },
    {
      "actual": 2.71,
      "predicted": 2.64,
      "district": "Manikganj",
      "season": "Aman"
    },
    {
      "actual": 2.11,
      "predicted": 2.15,
      "district": "Manikganj",
      "season": "Aus"
    },
    {
      "actual": 2.17,
      "predicted": 2.1,
      "district": "Manikganj",
      "season": "Aus"
    },
    {
      "actual": 4.12,
      "predicted": 4.28,
      "district": "Manikganj",
      "season": "Boro"
    },
    {
      "actual": 4.37,
      "predicted": 3.89,
      "district": "Manikganj",
      "season": "Boro"
    },
    {
      "actual": 2.58,
      "predicted": 2.55,
      "district": "Meherpur",
      "season": "Aman"
    },
    {
      "actual": 2.66,
      "predicted": 2.62,
      "district": "Meherpur",
      "season": "Aman"
    },
    {
      "actual": 2.07,
      "predicted": 2.15,
      "district": "Meherpur",
      "season": "Aus"
    },
    {
      "actual": 2.21,
      "predicted": 2.07,
      "district": "Meherpur",
      "season": "Aus"
    },
    {
      "actual": 4.24,
      "predicted": 4.31,
      "district": "Meherpur",
      "season": "Boro"
    },
    {
      "actual": 4.3,
      "predicted": 3.9,
      "district": "Meherpur",
      "season": "Boro"
    },
    {
      "actual": 2.11,
      "predicted": 2.57,
      "district": "Moulvibazar",
      "season": "Aman"
    },
    {
      "actual": 2.74,
      "predicted": 2.46,
      "district": "Moulvibazar",
      "season": "Aman"
    },
    {
      "actual": 1.72,
      "predicted": 2.12,
      "district": "Moulvibazar",
      "season": "Aus"
    },
    {
      "actual": 2.18,
      "predicted": 1.96,
      "district": "Moulvibazar",
      "season": "Aus"
    },
    {
      "actual": 3.41,
      "predicted": 4.24,
      "district": "Moulvibazar",
      "season": "Boro"
    },
    {
      "actual": 4.37,
      "predicted": 3.71,
      "district": "Moulvibazar",
      "season": "Boro"
    },
    {
      "actual": 2.63,
      "predicted": 2.54,
      "district": "Munshiganj",
      "season": "Aman"
    },
    {
      "actual": 2.71,
      "predicted": 2.63,
      "district": "Munshiganj",
      "season": "Aman"
    },
    {
      "actual": 2.05,
      "predicted": 2.12,
      "district": "Munshiganj",
      "season": "Aus"
    },
    {
      "actual": 2.2,
      "predicted": 2.09,
      "district": "Munshiganj",
      "season": "Aus"
    },
    {
      "actual": 4.5,
      "predicted": 4.27,
      "district": "Munshiganj",
      "season": "Boro"
    },
    {
      "actual": 4.37,
      "predicted": 4.05,
      "district": "Munshiganj",
      "season": "Boro"
    },
    {
      "actual": 2.87,
      "predicted": 2.84,
      "district": "Mymensingh",
      "season": "Aman"
    },
    {
      "actual": 3.06,
      "predicted": 2.92,
      "district": "Mymensingh",
      "season": "Aman"
    },
    {
      "actual": 2.31,
      "predicted": 2.31,
      "district": "Mymensingh",
      "season": "Aus"
    },
    {
      "actual": 2.35,
      "predicted": 2.33,
      "district": "Mymensingh",
      "season": "Aus"
    },
    {
      "actual": 4.55,
      "predicted": 4.65,
      "district": "Mymensingh",
      "season": "Boro"
    },
    {
      "actual": 5.08,
      "predicted": 4.53,
      "district": "Mymensingh",
      "season": "Boro"
    },
    {
      "actual": 3.08,
      "predicted": 2.94,
      "district": "Naogaon",
      "season": "Aman"
    },
    {
      "actual": 3.1,
      "predicted": 2.97,
      "district": "Naogaon",
      "season": "Aman"
    },
    {
      "actual": 2.43,
      "predicted": 2.46,
      "district": "Naogaon",
      "season": "Aus"
    },
    {
      "actual": 2.49,
      "predicted": 2.5,
      "district": "Naogaon",
      "season": "Aus"
    },
    {
      "actual": 4.81,
      "predicted": 4.76,
      "district": "Naogaon",
      "season": "Boro"
    },
    {
      "actual": 4.99,
      "predicted": 4.68,
      "district": "Naogaon",
      "season": "Boro"
    },
    {
      "actual": 2.62,
      "predicted": 2.52,
      "district": "Narail",
      "season": "Aman"
    },
    {
      "actual": 2.58,
      "predicted": 2.63,
      "district": "Narail",
      "season": "Aman"
    },
    {
      "actual": 2.02,
      "predicted": 2.13,
      "district": "Narail",
      "season": "Aus"
    },
    {
      "actual": 2.11,
      "predicted": 2.06,
      "district": "Narail",
      "season": "Aus"
    },
    {
      "actual": 4.41,
      "predicted": 4.28,
      "district": "Narail",
      "season": "Boro"
    },
    {
      "actual": 4.23,
      "predicted": 3.96,
      "district": "Narail",
      "season": "Boro"
    },
    {
      "actual": 2.55,
      "predicted": 2.37,
      "district": "Narayanganj",
      "season": "Aman"
    },
    {
      "actual": 2.55,
      "predicted": 2.42,
      "district": "Narayanganj",
      "season": "Aman"
    },
    {
      "actual": 2.08,
      "predicted": 2.12,
      "district": "Narayanganj",
      "season": "Aus"
    },
    {
      "actual": 2.06,
      "predicted": 2.07,
      "district": "Narayanganj",
      "season": "Aus"
    },
    {
      "actual": 4.01,
      "predicted": 4.13,
      "district": "Narayanganj",
      "season": "Boro"
    },
    {
      "actual": 4.23,
      "predicted": 3.77,
      "district": "Narayanganj",
      "season": "Boro"
    },
    {
      "actual": 2.6,
      "predicted": 2.56,
      "district": "Narsingdi",
      "season": "Aman"
    },
    {
      "actual": 2.71,
      "predicted": 2.62,
      "district": "Narsingdi",
      "season": "Aman"
    },
    {
      "actual": 2.13,
      "predicted": 2.14,
      "district": "Narsingdi",
      "season": "Aus"
    },
    {
      "actual": 2.15,
      "predicted": 2.1,
      "district": "Narsingdi",
      "season": "Aus"
    },
    {
      "actual": 4.16,
      "predicted": 4.29,
      "district": "Narsingdi",
      "season": "Boro"
    },
    {
      "actual": 4.49,
      "predicted": 3.88,
      "district": "Narsingdi",
      "season": "Boro"
    },
    {
      "actual": 2.69,
      "predicted": 2.57,
      "district": "Natore",
      "season": "Aman"
    },
    {
      "actual": 2.7,
      "predicted": 2.65,
      "district": "Natore",
      "season": "Aman"
    },
    {
      "actual": 2.06,
      "predicted": 2.13,
      "district": "Natore",
      "season": "Aus"
    },
    {
      "actual": 2.16,
      "predicted": 2.09,
      "district": "Natore",
      "season": "Aus"
    },
    {
      "actual": 4.13,
      "predicted": 4.27,
      "district": "Natore",
      "season": "Boro"
    },
    {
      "actual": 4.3,
      "predicted": 3.86,
      "district": "Natore",
      "season": "Boro"
    },
    {
      "actual": 2.57,
      "predicted": 2.54,
      "district": "Netrokona",
      "season": "Aman"
    },
    {
      "actual": 2.6,
      "predicted": 2.62,
      "district": "Netrokona",
      "season": "Aman"
    },
    {
      "actual": 2.14,
      "predicted": 2.17,
      "district": "Netrokona",
      "season": "Aus"
    },
    {
      "actual": 2.18,
      "predicted": 2.09,
      "district": "Netrokona",
      "season": "Aus"
    },
    {
      "actual": 4.22,
      "predicted": 4.22,
      "district": "Netrokona",
      "season": "Boro"
    },
    {
      "actual": 4.46,
      "predicted": 3.93,
      "district": "Netrokona",
      "season": "Boro"
    },
    {
      "actual": 2.66,
      "predicted": 2.55,
      "district": "Nilphamari",
      "season": "Aman"
    },
    {
      "actual": 2.67,
      "predicted": 2.64,
      "district": "Nilphamari",
      "season": "Aman"
    },
    {
      "actual": 2.11,
      "predicted": 2.1,
      "district": "Nilphamari",
      "season": "Aus"
    },
    {
      "actual": 2.14,
      "predicted": 2.09,
      "district": "Nilphamari",
      "season": "Aus"
    },
    {
      "actual": 4.13,
      "predicted": 4.33,
      "district": "Nilphamari",
      "season": "Boro"
    },
    {
      "actual": 4.27,
      "predicted": 3.86,
      "district": "Nilphamari",
      "season": "Boro"
    },
    {
      "actual": 2.61,
      "predicted": 2.55,
      "district": "Noakhali",
      "season": "Aman"
    },
    {
      "actual": 2.71,
      "predicted": 2.61,
      "district": "Noakhali",
      "season": "Aman"
    },
    {
      "actual": 2.1,
      "predicted": 2.15,
      "district": "Noakhali",
      "season": "Aus"
    },
    {
      "actual": 2.12,
      "predicted": 2.06,
      "district": "Noakhali",
      "season": "Aus"
    },
    {
      "actual": 4.1,
      "predicted": 4.23,
      "district": "Noakhali",
      "season": "Boro"
    },
    {
      "actual": 4.37,
      "predicted": 3.87,
      "district": "Noakhali",
      "season": "Boro"
    },
    {
      "actual": 2.62,
      "predicted": 2.55,
      "district": "Pabna",
      "season": "Aman"
    },
    {
      "actual": 2.73,
      "predicted": 2.62,
      "district": "Pabna",
      "season": "Aman"
    },
    {
      "actual": 2.11,
      "predicted": 2.13,
      "district": "Pabna",
      "season": "Aus"
    },
    {
      "actual": 2.18,
      "predicted": 2.09,
      "district": "Pabna",
      "season": "Aus"
    },
    {
      "actual": 4.25,
      "predicted": 4.27,
      "district": "Pabna",
      "season": "Boro"
    },
    {
      "actual": 4.23,
      "predicted": 3.9,
      "district": "Pabna",
      "season": "Boro"
    },
    {
      "actual": 2.63,
      "predicted": 2.54,
      "district": "Panchagarh",
      "season": "Aman"
    },
    {
      "actual": 2.62,
      "predicted": 2.64,
      "district": "Panchagarh",
      "season": "Aman"
    },
    {
      "actual": 2.17,
      "predicted": 2.17,
      "district": "Panchagarh",
      "season": "Aus"
    },
    {
      "actual": 2.13,
      "predicted": 2.11,
      "district": "Panchagarh",
      "season": "Aus"
    },
    {
      "actual": 4.22,
      "predicted": 4.3,
      "district": "Panchagarh",
      "season": "Boro"
    },
    {
      "actual": 4.37,
      "predicted": 3.87,
      "district": "Panchagarh",
      "season": "Boro"
    },
    {
      "actual": 2.56,
      "predicted": 2.56,
      "district": "Patuakhali",
      "season": "Aman"
    },
    {
      "actual": 2.65,
      "predicted": 2.59,
      "district": "Patuakhali",
      "season": "Aman"
    },
    {
      "actual": 2.04,
      "predicted": 2.13,
      "district": "Patuakhali",
      "season": "Aus"
    },
    {
      "actual": 2.1,
      "predicted": 2.06,
      "district": "Patuakhali",
      "season": "Aus"
    },
    {
      "actual": 4.15,
      "predicted": 4.26,
      "district": "Patuakhali",
      "season": "Boro"
    },
    {
      "actual": 4.48,
      "predicted": 3.84,
      "district": "Patuakhali",
      "season": "Boro"
    },
    {
      "actual": 2.69,
      "predicted": 2.56,
      "district": "Pirojpur",
      "season": "Aman"
    },
    {
      "actual": 2.76,
      "predicted": 2.64,
      "district": "Pirojpur",
      "season": "Aman"
    },
    {
      "actual": 2.08,
      "predicted": 2.11,
      "district": "Pirojpur",
      "season": "Aus"
    },
    {
      "actual": 2.21,
      "predicted": 2.08,
      "district": "Pirojpur",
      "season": "Aus"
    },
    {
      "actual": 4.16,
      "predicted": 4.19,
      "district": "Pirojpur",
      "season": "Boro"
    },
    {
      "actual": 4.44,
      "predicted": 3.92,
      "district": "Pirojpur",
      "season": "Boro"
    },
    {
      "actual": 2.51,
      "predicted": 2.51,
      "district": "Rajbari",
      "season": "Aman"
    },
    {
      "actual": 2.66,
      "predicted": 2.6,
      "district": "Rajbari",
      "season": "Aman"
    },
    {
      "actual": 2.05,
      "predicted": 2.14,
      "district": "Rajbari",
      "season": "Aus"
    },
    {
      "actual": 2.15,
      "predicted": 2.07,
      "district": "Rajbari",
      "season": "Aus"
    },
    {
      "actual": 4.08,
      "predicted": 4.26,
      "district": "Rajbari",
      "season": "Boro"
    },
    {
      "actual": 4.26,
      "predicted": 3.87,
      "district": "Rajbari",
      "season": "Boro"
    },
    {
      "actual": 2.61,
      "predicted": 2.53,
      "district": "Rajshahi",
      "season": "Aman"
    },
    {
      "actual": 2.64,
      "predicted": 2.64,
      "district": "Rajshahi",
      "season": "Aman"
    },
    {
      "actual": 2.16,
      "predicted": 2.12,
      "district": "Rajshahi",
      "season": "Aus"
    },
    {
      "actual": 2.15,
      "predicted": 2.12,
      "district": "Rajshahi",
      "season": "Aus"
    },
    {
      "actual": 4.07,
      "predicted": 4.29,
      "district": "Rajshahi",
      "season": "Boro"
    },
    {
      "actual": 4.3,
      "predicted": 3.83,
      "district": "Rajshahi",
      "season": "Boro"
    },
    {
      "actual": 1.98,
      "predicted": 2.03,
      "district": "Rangamati",
      "season": "Aman"
    },
    {
      "actual": 2.11,
      "predicted": 2.03,
      "district": "Rangamati",
      "season": "Aman"
    },
    {
      "actual": 1.59,
      "predicted": 1.69,
      "district": "Rangamati",
      "season": "Aus"
    },
    {
      "actual": 1.69,
      "predicted": 1.67,
      "district": "Rangamati",
      "season": "Aus"
    },
    {
      "actual": 3.21,
      "predicted": 3.27,
      "district": "Rangamati",
      "season": "Boro"
    },
    {
      "actual": 3.39,
      "predicted": 3.18,
      "district": "Rangamati",
      "season": "Boro"
    },
    {
      "actual": 2.63,
      "predicted": 2.54,
      "district": "Rangpur",
      "season": "Aman"
    },
    {
      "actual": 2.71,
      "predicted": 2.63,
      "district": "Rangpur",
      "season": "Aman"
    },
    {
      "actual": 2.04,
      "predicted": 2.12,
      "district": "Rangpur",
      "season": "Aus"
    },
    {
      "actual": 2.15,
      "predicted": 2.07,
      "district": "Rangpur",
      "season": "Aus"
    },
    {
      "actual": 4.21,
      "predicted": 4.27,
      "district": "Rangpur",
      "season": "Boro"
    },
    {
      "actual": 4.27,
      "predicted": 3.92,
      "district": "Rangpur",
      "season": "Boro"
    },
    {
      "actual": 2.57,
      "predicted": 2.57,
      "district": "Satkhira",
      "season": "Aman"
    },
    {
      "actual": 2.65,
      "predicted": 2.59,
      "district": "Satkhira",
      "season": "Aman"
    },
    {
      "actual": 2.04,
      "predicted": 2.17,
      "district": "Satkhira",
      "season": "Aus"
    },
    {
      "actual": 2.14,
      "predicted": 2.04,
      "district": "Satkhira",
      "season": "Aus"
    },
    {
      "actual": 4.09,
      "predicted": 4.21,
      "district": "Satkhira",
      "season": "Boro"
    },
    {
      "actual": 4.33,
      "predicted": 3.86,
      "district": "Satkhira",
      "season": "Boro"
    },
    {
      "actual": 2.61,
      "predicted": 2.57,
      "district": "Shariatpur",
      "season": "Aman"
    },
    {
      "actual": 2.65,
      "predicted": 2.59,
      "district": "Shariatpur",
      "season": "Aman"
    },
    {
      "actual": 2.19,
      "predicted": 2.14,
      "district": "Shariatpur",
      "season": "Aus"
    },
    {
      "actual": 2.12,
      "predicted": 2.11,
      "district": "Shariatpur",
      "season": "Aus"
    },
    {
      "actual": 4.11,
      "predicted": 4.25,
      "district": "Shariatpur",
      "season": "Boro"
    },
    {
      "actual": 4.33,
      "predicted": 3.85,
      "district": "Shariatpur",
      "season": "Boro"
    },
    {
      "actual": 2.71,
      "predicted": 2.56,
      "district": "Sherpur",
      "season": "Aman"
    },
    {
      "actual": 2.69,
      "predicted": 2.64,
      "district": "Sherpur",
      "season": "Aman"
    },
    {
      "actual": 2.12,
      "predicted": 2.13,
      "district": "Sherpur",
      "season": "Aus"
    },
    {
      "actual": 2.22,
      "predicted": 2.1,
      "district": "Sherpur",
      "season": "Aus"
    },
    {
      "actual": 4.2,
      "predicted": 4.26,
      "district": "Sherpur",
      "season": "Boro"
    },
    {
      "actual": 4.32,
      "predicted": 3.9,
      "district": "Sherpur",
      "season": "Boro"
    },
    {
      "actual": 2.66,
      "predicted": 2.58,
      "district": "Sirajganj",
      "season": "Aman"
    },
    {
      "actual": 2.74,
      "predicted": 2.67,
      "district": "Sirajganj",
      "season": "Aman"
    },
    {
      "actual": 2.12,
      "predicted": 2.19,
      "district": "Sirajganj",
      "season": "Aus"
    },
    {
      "actual": 2.2,
      "predicted": 2.09,
      "district": "Sirajganj",
      "season": "Aus"
    },
    {
      "actual": 4.36,
      "predicted": 4.26,
      "district": "Sirajganj",
      "season": "Boro"
    },
    {
      "actual": 4.31,
      "predicted": 4.06,
      "district": "Sirajganj",
      "season": "Boro"
    },
    {
      "actual": 2.07,
      "predicted": 2.55,
      "district": "Sunamganj",
      "season": "Aman"
    },
    {
      "actual": 2.64,
      "predicted": 2.44,
      "district": "Sunamganj",
      "season": "Aman"
    },
    {
      "actual": 1.71,
      "predicted": 2.09,
      "district": "Sunamganj",
      "season": "Aus"
    },
    {
      "actual": 2.29,
      "predicted": 1.96,
      "district": "Sunamganj",
      "season": "Aus"
    },
    {
      "actual": 3.42,
      "predicted": 4.06,
      "district": "Sunamganj",
      "season": "Boro"
    },
    {
      "actual": 4.4,
      "predicted": 3.73,
      "district": "Sunamganj",
      "season": "Boro"
    },
    {
      "actual": 2.1,
      "predicted": 2.56,
      "district": "Sylhet",
      "season": "Aman"
    },
    {
      "actual": 2.72,
      "predicted": 2.39,
      "district": "Sylhet",
      "season": "Aman"
    },
    {
      "actual": 1.73,
      "predicted": 2.13,
      "district": "Sylhet",
      "season": "Aus"
    },
    {
      "actual": 2.12,
      "predicted": 1.93,
      "district": "Sylhet",
      "season": "Aus"
    },
    {
      "actual": 3.41,
      "predicted": 4.01,
      "district": "Sylhet",
      "season": "Boro"
    },
    {
      "actual": 4.28,
      "predicted": 3.73,
      "district": "Sylhet",
      "season": "Boro"
    },
    {
      "actual": 2.76,
      "predicted": 2.62,
      "district": "Tangail",
      "season": "Aman"
    },
    {
      "actual": 2.8,
      "predicted": 2.75,
      "district": "Tangail",
      "season": "Aman"
    },
    {
      "actual": 2.25,
      "predicted": 2.2,
      "district": "Tangail",
      "season": "Aus"
    },
    {
      "actual": 2.2,
      "predicted": 2.19,
      "district": "Tangail",
      "season": "Aus"
    },
    {
      "actual": 4.36,
      "predicted": 4.39,
      "district": "Tangail",
      "season": "Boro"
    },
    {
      "actual": 4.62,
      "predicted": 4.28,
      "district": "Tangail",
      "season": "Boro"
    },
    {
      "actual": 2.51,
      "predicted": 2.5,
      "district": "Thakurgaon",
      "season": "Aman"
    },
    {
      "actual": 2.7,
      "predicted": 2.58,
      "district": "Thakurgaon",
      "season": "Aman"
    },
    {
      "actual": 2.16,
      "predicted": 2.13,
      "district": "Thakurgaon",
      "season": "Aus"
    },
    {
      "actual": 2.13,
      "predicted": 2.11,
      "district": "Thakurgaon",
      "season": "Aus"
    },
    {
      "actual": 4.29,
      "predicted": 4.28,
      "district": "Thakurgaon",
      "season": "Boro"
    },
    {
      "actual": 4.43,
      "predicted": 3.92,
      "district": "Thakurgaon",
      "season": "Boro"
    }
  ],
  "residual_distribution": [
    {
      "bin": -0.42,
      "count": 3
    },
    {
      "bin": -0.36,
      "count": 2
    },
    {
      "bin": -0.3,
      "count": 0
    },
    {
      "bin": -0.24,
      "count": 2
    },
    {
      "bin": -0.18,
      "count": 6
    },
    {
      "bin": -0.12,
      "count": 19
    },
    {
      "bin": -0.06,
      "count": 52
    },
    {
      "bin": 0.0,
      "count": 64
    },
    {
      "bin": 0.06,
      "count": 89
    },
    {
      "bin": 0.12,
      "count": 55
    },
    {
      "bin": 0.18,
      "count": 18
    },
    {
      "bin": 0.24,
      "count": 6
    },
    {
      "bin": 0.3,
      "count": 8
    },
    {
      "bin": 0.36,
      "count": 14
    },
    {
      "bin": 0.42,
      "count": 12
    }
  ],
  "district_mae": [
    {
      "district": "Bandarban",
      "mae": 0.0667
    },
    {
      "district": "Khagrachhari",
      "mae": 0.08
    },
    {
      "district": "Madaripur",
      "mae": 0.085
    },
    {
      "district": "Rangamati",
      "mae": 0.0867
    },
    {
      "district": "Gopalganj",
      "mae": 0.0933
    },
    {
      "district": "Jamalpur",
      "mae": 0.0983
    },
    {
      "district": "Kishoreganj",
      "mae": 0.1
    },
    {
      "district": "Jashore",
      "mae": 0.1017
    },
    {
      "district": "Brahmanbaria",
      "mae": 0.1033
    },
    {
      "district": "Tangail",
      "mae": 0.1033
    },
    {
      "district": "Chattogram",
      "mae": 0.105
    },
    {
      "district": "Faridpur",
      "mae": 0.1067
    },
    {
      "district": "Pabna",
      "mae": 0.1067
    },
    {
      "district": "Gazipur",
      "mae": 0.11
    },
    {
      "district": "Naogaon",
      "mae": 0.1117
    },
    {
      "district": "Bhola",
      "mae": 0.1133
    },
    {
      "district": "Sirajganj",
      "mae": 0.1133
    },
    {
      "district": "Netrokona",
      "mae": 0.1167
    },
    {
      "district": "Thakurgaon",
      "mae": 0.1167
    },
    {
      "district": "Chapainawabganj",
      "mae": 0.1183
    },
    {
      "district": "Narail",
      "mae": 0.1183
    },
    {
      "district": "Panchagarh",
      "mae": 0.1183
    },
    {
      "district": "Cumilla",
      "mae": 0.12
    },
    {
      "district": "Cox'S Bazar",
      "mae": 0.1217
    },
    {
      "district": "Jhenaidah",
      "mae": 0.1217
    },
    {
      "district": "Rangpur",
      "mae": 0.1233
    },
    {
      "district": "Dhaka",
      "mae": 0.125
    },
    {
      "district": "Gaibandha",
      "mae": 0.125
    },
    {
      "district": "Kurigram",
      "mae": 0.1267
    },
    {
      "district": "Meherpur",
      "mae": 0.1267
    },
    {
      "district": "Bogura",
      "mae": 0.1283
    },
    {
      "district": "Lakshmipur",
      "mae": 0.1283
    },
    {
      "district": "Chandpur",
      "mae": 0.13
    },
    {
      "district": "Khulna",
      "mae": 0.13
    },
    {
      "district": "Shariatpur",
      "mae": 0.13
    },
    {
      "district": "Dinajpur",
      "mae": 0.1317
    },
    {
      "district": "Rajbari",
      "mae": 0.1333
    },
    {
      "district": "Nilphamari",
      "mae": 0.135
    },
    {
      "district": "Sherpur",
      "mae": 0.135
    },
    {
      "district": "Barishal",
      "mae": 0.1367
    },
    {
      "district": "Joypurhat",
      "mae": 0.1383
    },
    {
      "district": "Magura",
      "mae": 0.1383
    },
    {
      "district": "Mymensingh",
      "mae": 0.14
    },
    {
      "district": "Rajshahi",
      "mae": 0.14
    },
    {
      "district": "Jhalokati",
      "mae": 0.1417
    },
    {
      "district": "Chuadanga",
      "mae": 0.145
    },
    {
      "district": "Lalmonirhat",
      "mae": 0.145
    },
    {
      "district": "Satkhira",
      "mae": 0.1467
    },
    {
      "district": "Natore",
      "mae": 0.1483
    },
    {
      "district": "Bagerhat",
      "mae": 0.15
    },
    {
      "district": "Munshiganj",
      "mae": 0.15
    },
    {
      "district": "Noakhali",
      "mae": 0.15
    },
    {
      "district": "Manikganj",
      "mae": 0.1533
    },
    {
      "district": "Narsingdi",
      "mae": 0.155
    },
    {
      "district": "Narayanganj",
      "mae": 0.1567
    },
    {
      "district": "Patuakhali",
      "mae": 0.1567
    },
    {
      "district": "Pirojpur",
      "mae": 0.16
    },
    {
      "district": "Barguna",
      "mae": 0.1683
    },
    {
      "district": "Feni",
      "mae": 0.2133
    },
    {
      "district": "Kushtia",
      "mae": 0.2133
    },
    {
      "district": "Sylhet",
      "mae": 0.4217
    },
    {
      "district": "Habiganj",
      "mae": 0.4483
    },
    {
      "district": "Sunamganj",
      "mae": 0.45
    },
    {
      "district": "Moulvibazar",
      "mae": 0.475
    }
  ],
  "cv_folds": [
    {
      "fold": "Fold 1 (2018)",
      "r2": 96.96,
      "rmse": 0.1591,
      "mae": 0.1142
    },
    {
      "fold": "Fold 2 (2019)",
      "r2": 98.25,
      "rmse": 0.1227,
      "mae": 0.0834
    },
    {
      "fold": "Fold 3 (2020)",
      "r2": 98.1,
      "rmse": 0.1221,
      "mae": 0.0827
    },
    {
      "fold": "Fold 4 (2021)",
      "r2": 97.67,
      "rmse": 0.1428,
      "mae": 0.0991
    }
  ],
  "global_metrics": {
    "r2": 98.23,
    "rmse": 0.1253,
    "mae": 0.0865,
    "mape": 3.12
  }
}